pyBCabs/__init__.py
pyBCabs/retrieval.py
pyBCabs-0.0.1.dist-info/LICENSE.md
pyBCabs-0.0.1.dist-info/METADATA
pyBCabs-0.0.1.dist-info/WHEEL
pyBCabs-0.0.1.dist-info/top_level.txt
pyBCabs-0.0.1.dist-info/RECORD
